streamlit_lightweight_charts/__init__.py
streamlit_lightweight_charts/dataSamples.py
streamlit_lightweight_charts/frontend/build/asset-manifest.json
streamlit_lightweight_charts/frontend/build/index.html
streamlit_lightweight_charts/frontend/build/static/js/2.49734e1f.chunk.js
streamlit_lightweight_charts/frontend/build/static/js/2.49734e1f.chunk.js.LICENSE.txt
streamlit_lightweight_charts/frontend/build/static/js/2.49734e1f.chunk.js.map
streamlit_lightweight_charts/frontend/build/static/js/main.770440ff.chunk.js
streamlit_lightweight_charts/frontend/build/static/js/main.770440ff.chunk.js.map
streamlit_lightweight_charts/frontend/build/static/js/runtime-main.ae41c458.js
streamlit_lightweight_charts/frontend/build/static/js/runtime-main.ae41c458.js.map
streamlit_tradingview_charts-0.1.0.dist-info/LICENSE
streamlit_tradingview_charts-0.1.0.dist-info/WHEEL
streamlit_tradingview_charts-0.1.0.dist-info/METADATA
streamlit_tradingview_charts-0.1.0.dist-info/RECORD
