Metadata-Version: 2.1
Name: streamlit-tradingview-charts
Version: 0.1.0
Summary: Wrapper for TradingView `lightweight-charts`
Home-page: https://github.com/lokiarya/streamlit-lightweight-charts
License: MIT
Author: Loki Arya
Author-email: loki.arya+osdev@gmail.com
Requires-Python: >=3.6,<4.0
Classifier: License :: OSI Approved :: MIT License
Classifier: Programming Language :: Python :: 3
Classifier: Programming Language :: Python :: 3.10
Classifier: Programming Language :: Python :: 3.6
Classifier: Programming Language :: Python :: 3.7
Classifier: Programming Language :: Python :: 3.8
Classifier: Programming Language :: Python :: 3.9
Requires-Dist: streamlit (>=1.27.2,<2.0.0)
Project-URL: Repository, https://github.com/lokiarya/streamlit-lightweight-charts
